{
  "dl-RD-01": { "name": "Rithala", "lat": 28.7209, "lon": 77.1070 },
  "dl-RD-02": { "name": "Rohini West", "lat": 28.7156, "lon": 77.1160 },
  "dl-RD-03": { "name": "Rohini East", "lat": 28.7093, "lon": 77.1278 },
  "dl-RD-04": { "name": "Pitam Pura", "lat": 28.7034, "lon": 77.1316 },
  "dl-RD-05": { "name": "Kohat Enclave", "lat": 28.6975, "lon": 77.1370 },
  "dl-RD-06": { "name": "Netaji Subhash Place", "lat": 28.6911, "lon": 77.1503 },
  "dl-RD-07": { "name": "Keshav Puram", "lat": 28.6855, "lon": 77.1553 },
  "dl-RD-08": { "name": "Kanhaiya Nagar", "lat": 28.6815, "lon": 77.1641 },
  "dl-RD-09": { "name": "Inderlok", "lat": 28.6732, "lon": 77.1713 },
  "dl-RD-10": { "name": "Pratap Nagar", "lat": 28.6717, "lon": 77.1837 },
  "dl-RD-11": { "name": "Pul Bangash", "lat": 28.6710, "lon": 77.1960 },
  "dl-RD-12": { "name": "Tis Hazari", "lat": 28.6684, "lon": 77.2100 },
  "dl-RD-13": { "name": "Kashmere Gate", "lat": 28.6674, "lon": 77.2280 },
  "dl-RD-14": { "name": "Shastri Park", "lat": 28.6678, "lon": 77.2462 },
  "dl-RD-15": { "name": "Seelampur", "lat": 28.6680, "lon": 77.2592 },
  "dl-RD-16": { "name": "Welcome", "lat": 28.6729, "lon": 77.2650 },
  "dl-RD-17": { "name": "Shahdara", "lat": 28.6740, "lon": 77.2880 },
  "dl-RD-18": { "name": "Mansarovar Park", "lat": 28.6728, "lon": 77.2979 },
  "dl-RD-19": { "name": "Jhilmil", "lat": 28.6734, "lon": 77.3107 },
  "dl-RD-20": { "name": "Dilshad Garden", "lat": 28.6760, "lon": 77.3210 },
  "dl-RD-21": { "name": "Shaheed Nagar", "lat": 28.6740, "lon": 77.3340 },
  "dl-RD-22": { "name": "Raj Bagh", "lat": 28.6703, "lon": 77.3423 },
  "dl-RD-23": { "name": "Major Mohit Sharma Rajendra Nagar", "lat": 28.6671, "lon": 77.3549 },
  "dl-RD-24": { "name": "Shyam Park", "lat": 28.6697, "lon": 77.3680 },
  "dl-RD-25": { "name": "Mohan Nagar", "lat": 28.6710, "lon": 77.3790 },
  "dl-RD-26": { "name": "Arthala", "lat": 28.6701, "lon": 77.3918 },
  "dl-RD-27": { "name": "Hindon River", "lat": 28.6710, "lon": 77.3995 },
  "dl-RD-28": { "name": "Shaheed Sthal", "lat": 28.6725, "lon": 77.4130 },

  "dl-YL-01": { "name": "Samaypur Badli", "lat": 28.7448, "lon": 77.1387 },
  "dl-YL-02": { "name": "Rohini Sector 18-19", "lat": 28.7383, "lon": 77.1393 },
  "dl-YL-03": { "name": "Haiderpur Badli Mor", "lat": 28.7271, "lon": 77.1533 },
  "dl-YL-04": { "name": "Jahangirpuri", "lat": 28.7258, "lon": 77.1632 },
  "dl-YL-05": { "name": "Adarsh Nagar", "lat": 28.7169, "lon": 77.1706 },
  "dl-YL-06": { "name": "Azadpur", "lat": 28.7073, "lon": 77.1792 },
  "dl-YL-07": { "name": "Model Town", "lat": 28.6993, "lon": 77.1898 },
  "dl-YL-08": { "name": "GTB Nagar", "lat": 28.6982, "lon": 77.2009 },
  "dl-YL-09": { "name": "Vishwavidyalaya", "lat": 28.6939, "lon": 77.2113 },
  "dl-YL-10": { "name": "Vidhan Sabha", "lat": 28.6885, "lon": 77.2188 },
  "dl-YL-11": { "name": "Civil Lines", "lat": 28.6818, "lon": 77.2225 },
  "dl-YL-12": { "name": "Kashmere Gate", "lat": 28.6674, "lon": 77.2280 },
  "dl-YL-13": { "name": "Chandni Chowk", "lat": 28.6566, "lon": 77.2305 },
  "dl-YL-14": { "name": "Chawri Bazar", "lat": 28.6507, "lon": 77.2262 },
  "dl-YL-15": { "name": "New Delhi", "lat": 28.6427, "lon": 77.2207 },
  "dl-YL-16": { "name": "Rajiv Chowk", "lat": 28.6328, "lon": 77.2197 },
  "dl-YL-17": { "name": "Patel Chowk", "lat": 28.6243, "lon": 77.2143 },
  "dl-YL-18": { "name": "Central Secretariat", "lat": 28.6148, "lon": 77.2115 },
  "dl-YL-19": { "name": "Udyog Bhawan", "lat": 28.6097, "lon": 77.2094 },
  "dl-YL-20": { "name": "Lok Kalyan Marg", "lat": 28.6016, "lon": 77.2063 },
  "dl-YL-21": { "name": "Jor Bagh", "lat": 28.5926, "lon": 77.2041 },
  "dl-YL-22": { "name": "INA", "lat": 28.5860, "lon": 77.2060 },
  "dl-YL-23": { "name": "AIIMS", "lat": 28.5690, "lon": 77.2079 },
  "dl-YL-24": { "name": "Green Park", "lat": 28.5589, "lon": 77.2063 },
  "dl-YL-25": { "name": "Hauz Khas", "lat": 28.5438, "lon": 77.2065 },
  "dl-YL-26": { "name": "Malviya Nagar", "lat": 28.5282, "lon": 77.2095 },
  "dl-YL-27": { "name": "Saket", "lat": 28.5201, "lon": 77.2020 },
  "dl-YL-28": { "name": "Qutub Minar", "lat": 28.5130, "lon": 77.1856 },
  "dl-YL-29": { "name": "Chhatarpur", "lat": 28.5069, "lon": 77.1747 },
  "dl-YL-30": { "name": "Sultanpur", "lat": 28.4976, "lon": 77.1570 },
  "dl-YL-31": { "name": "Ghitorni", "lat": 28.4938, "lon": 77.1454 },
  "dl-YL-32": { "name": "Arjan Garh", "lat": 28.4846, "lon": 77.1282 },
  "dl-YL-33": { "name": "Guru Dronacharya", "lat": 28.4822, "lon": 77.1053 },
  "dl-YL-34": { "name": "Sikandarpur", "lat": 28.4793, "lon": 77.0928 },
  "dl-YL-35": { "name": "MG Road", "lat": 28.4795, "lon": 77.0822 },
  "dl-YL-36": { "name": "IFFCO Chowk", "lat": 28.4720, "lon": 77.0720 },
  "dl-YL-37": { "name": "HUDA City Centre", "lat": 28.4594, "lon": 77.0724 },

  "dl-BL-01": { "name": "Dwarka Sector 21", "lat": 28.5523, "lon": 77.0583 },
  "dl-BL-02": { "name": "Dwarka Sector 8", "lat": 28.5631, "lon": 77.0654 },
  "dl-BL-03": { "name": "Dwarka Sector 9", "lat": 28.5718, "lon": 77.0657 },
  "dl-BL-04": { "name": "Dwarka Sector 10", "lat": 28.5810, "lon": 77.0620 },
  "dl-BL-05": { "name": "Dwarka Sector 11", "lat": 28.5872, "lon": 77.0553 },
  "dl-BL-06": { "name": "Dwarka Sector 12", "lat": 28.5927, "lon": 77.0476 },
  "dl-BL-07": { "name": "Dwarka Sector 13", "lat": 28.5957, "lon": 77.0390 },
  "dl-BL-08": { "name": "Dwarka Sector 14", "lat": 28.5948, "lon": 77.0302 },
  "dl-BL-09": { "name": "Dwarka", "lat": 28.5927, "lon": 77.0220 },
  "dl-BL-10": { "name": "Dwarka Mor", "lat": 28.6023, "lon": 77.0191 },
  "dl-BL-11": { "name": "Nawada", "lat": 28.6087, "lon": 77.0169 },
  "dl-BL-12": { "name": "Uttam Nagar West", "lat": 28.6148, "lon": 77.0220 },
  "dl-BL-13": { "name": "Uttam Nagar East", "lat": 28.6210, "lon": 77.0340 },
  "dl-BL-14": { "name": "Janakpuri West", "lat": 28.6290, "lon": 77.0502 },
  "dl-BL-15": { "name": "Janakpuri East", "lat": 28.6310, "lon": 77.0625 },
  "dl-BL-16": { "name": "Tilak Nagar", "lat": 28.6379, "lon": 77.0762 },
  "dl-BL-17": { "name": "Subhash Nagar", "lat": 28.6396, "lon": 77.0860 },
  "dl-BL-18": { "name": "Tagore Garden", "lat": 28.6437, "lon": 77.0947 },
  "dl-BL-19": { "name": "Rajouri Garden", "lat": 28.6480, "lon": 77.1102 },
  "dl-BL-20": { "name": "Ramesh Nagar", "lat": 28.6509, "lon": 77.1186 },
  "dl-BL-21": { "name": "Moti Nagar", "lat": 28.6544, "lon": 77.1322 },
  "dl-BL-22": { "name": "Kirti Nagar", "lat": 28.6554, "lon": 77.1447 },
  "dl-BL-23": { "name": "Shadipur", "lat": 28.6518, "lon": 77.1570 },
  "dl-BL-24": { "name": "Patel Nagar", "lat": 28.6513, "lon": 77.1671 },
  "dl-BL-25": { "name": "Rajendra Place", "lat": 28.6416, "lon": 77.1784 },
  "dl-BL-26": { "name": "Karol Bagh", "lat": 28.6441, "lon": 77.1912 },
  "dl-BL-27": { "name": "Jhandewalan", "lat": 28.6416, "lon": 77.2031 },
  "dl-BL-28": { "name": "R.K. Ashram Marg", "lat": 28.6384, "lon": 77.2098 },
  "dl-BL-29": { "name": "Rajiv Chowk", "lat": 28.6328, "lon": 77.2197 },
  "dl-BL-30": { "name": "Barakhamba Road", "lat": 28.6313, "lon": 77.2302 },
  "dl-BL-31": { "name": "Mandi House", "lat": 28.6258, "lon": 77.2343 },
  "dl-BL-32": { "name": "Pragati Maidan", "lat": 28.6204, "lon": 77.2442 },
  "dl-BL-33": { "name": "Indraprastha", "lat": 28.6168, "lon": 77.2505 },
  "dl-BL-34": { "name": "Yamuna Bank", "lat": 28.6139, "lon": 77.2639 },
  "dl-BL-35": { "name": "Laxmi Nagar", "lat": 28.6299, "lon": 77.2777 },
  "dl-BL-36": { "name": "Nirman Vihar", "lat": 28.6354, "lon": 77.2893 },
  "dl-BL-37": { "name": "Preet Vihar", "lat": 28.6392, "lon": 77.2972 },
  "dl-BL-38": { "name": "Karkarduma", "lat": 28.6456, "lon": 77.3068 },
  "dl-BL-39": { "name": "Anand Vihar ISBT", "lat": 28.6461, "lon": 77.3159 },
  "dl-BL-40": { "name": "Kaushambi", "lat": 28.6436, "lon": 77.3268 },
  "dl-BL-41": { "name": "Vaishali", "lat": 28.6424, "lon": 77.3396 },
  "dl-BL-42": { "name": "Akshardham", "lat": 28.6112, "lon": 77.2757 },
  "dl-BL-43": { "name": "Mayur Vihar Phase-I", "lat": 28.6049, "lon": 77.2897 },
  "dl-BL-44": { "name": "Mayur Vihar Extension", "lat": 28.5969, "lon": 77.2975 },
  "dl-BL-45": { "name": "New Ashok Nagar", "lat": 28.5892, "lon": 77.3064 },
  "dl-BL-46": { "name": "Noida Sector 15", "lat": 28.5846, "lon": 77.3158 },
  "dl-BL-47": { "name": "Noida Sector 16", "lat": 28.5775, "lon": 77.3239 },
  "dl-BL-48": { "name": "Noida Sector 18", "lat": 28.5702, "lon": 77.3276 },
  "dl-BL-49": { "name": "Botanical Garden", "lat": 28.5643, "lon": 77.3344 },
  "dl-BL-50": { "name": "Golf Course", "lat": 28.5563, "lon": 77.3412 },
  "dl-BL-51": { "name": "Noida City Centre", "lat": 28.5500, "lon": 77.3506 },
  "dl-BL-52": { "name": "Noida Sector 34", "lat": 28.5437, "lon": 77.3528 },
  "dl-BL-53": { "name": "Noida Sector 52", "lat": 28.5379, "lon": 77.3566 },
  "dl-BL-54": { "name": "Noida Sector 61", "lat": 28.5302, "lon": 77.3627 },
  "dl-BL-55": { "name": "Noida Sector 59", "lat": 28.5253, "lon": 77.3693 },
  "dl-BL-56": { "name": "Noida Sector 62", "lat": 28.5299, "lon": 77.3754 },
  "dl-BL-57": { "name": "Noida Electronic City", "lat": 28.5356, "lon": 77.3823 },

  "dl-GL-01": { "name": "Mundka", "lat": 28.6843, "lon": 77.0302 },
  "dl-GL-02": { "name": "Mundka Industrial Area", "lat": 28.6866, "lon": 77.0170 },
  "dl-GL-03": { "name": "Ghevra", "lat": 28.6890, "lon": 77.0020 },
  "dl-GL-04": { "name": "Tikri Kalan", "lat": 28.6917, "lon": 76.9870 },
  "dl-GL-05": { "name": "Tikri Border", "lat": 28.6943, "lon": 76.9714 },
  "dl-GL-06": { "name": "Pandit Shree Ram Sharma", "lat": 28.6918, "lon": 76.9560 },
  "dl-GL-07": { "name": "Bahadurgarh City", "lat": 28.6883, "lon": 76.9367 },
  "dl-GL-08": { "name": "Brigadier Hoshiar Singh", "lat": 28.6825, "lon": 76.9196 },
  "dl-GL-09": { "name": "Rajdhani Park", "lat": 28.6826, "lon": 77.0430 },
  "dl-GL-10": { "name": "Nangloi Railway Station", "lat": 28.6808, "lon": 77.0536 },
  "dl-GL-11": { "name": "Nangloi", "lat": 28.6797, "lon": 77.0632 },
  "dl-GL-12": { "name": "Maharaja Surajmal Stadium", "lat": 28.6770, "lon": 77.0771 },
  "dl-GL-13": { "name": "Udyog Nagar", "lat": 28.6777, "lon": 77.0880 },
  "dl-GL-14": { "name": "Peera Garhi", "lat": 28.6760, "lon": 77.0970 },
  "dl-GL-15": { "name": "Paschim Vihar West", "lat": 28.6731, "lon": 77.1068 },
  "dl-GL-16": { "name": "Paschim Vihar East", "lat": 28.6703, "lon": 77.1184 },
  "dl-GL-17": { "name": "Madipur", "lat": 28.6677, "lon": 77.1304 },
  "dl-GL-18": { "name": "Shivaji Park", "lat": 28.6680, "lon": 77.1400 },
  "dl-GL-19": { "name": "Punjabi Bagh", "lat": 28.6650, "lon": 77.1380 },
  "dl-GL-20": { "name": "Ashok Park Main", "lat": 28.6700, "lon": 77.1507 },
  "dl-GL-21": { "name": "Inderlok", "lat": 28.6732, "lon": 77.1713 },

  "dl-VL-01": { "name": "Kashmere Gate", "lat": 28.6674, "lon": 77.2280 },
  "dl-VL-02": { "name": "Lal Qila", "lat": 28.6567, "lon": 77.2412 },
  "dl-VL-03": { "name": "Jama Masjid", "lat": 28.6505, "lon": 77.2379 },
  "dl-VL-04": { "name": "Delhi Gate", "lat": 28.6422, "lon": 77.2413 },
  "dl-VL-05": { "name": "ITO", "lat": 28.6300, "lon": 77.2426 },
  "dl-VL-06": { "name": "Mandi House", "lat": 28.6258, "lon": 77.2343 },
  "dl-VL-07": { "name": "Janpath", "lat": 28.6191, "lon": 77.2217 },
  "dl-VL-08": { "name": "Central Secretariat", "lat": 28.6148, "lon": 77.2115 },
  "dl-VL-09": { "name": "Khan Market", "lat": 28.6004, "lon": 77.2278 },
  "dl-VL-10": { "name": "Jawaharlal Nehru Stadium", "lat": 28.5869, "lon": 77.2351 },
  "dl-VL-11": { "name": "Jangpura", "lat": 28.5816, "lon": 77.2414 },
  "dl-VL-12": { "name": "Lajpat Nagar", "lat": 28.5701, "lon": 77.2438 },
  "dl-VL-13": { "name": "Moolchand", "lat": 28.5651, "lon": 77.2369 },
  "dl-VL-14": { "name": "Kailash Colony", "lat": 28.5575, "lon": 77.2414 },
  "dl-VL-15": { "name": "Nehru Place", "lat": 28.5499, "lon": 77.2528 },
  "dl-VL-16": { "name": "Kalkaji Mandir", "lat": 28.5436, "lon": 77.2594 },
  "dl-VL-17": { "name": "Govind Puri", "lat": 28.5358, "lon": 77.2639 },
  "dl-VL-18": { "name": "Harkesh Nagar Okhla", "lat": 28.5276, "lon": 77.2680 },
  "dl-VL-19": { "name": "Jasola Apollo", "lat": 28.5215, "lon": 77.2768 },
  "dl-VL-20": { "name": "Sarita Vihar", "lat": 28.5096, "lon": 77.2908 },
  "dl-VL-21": { "name": "Mohan Estate", "lat": 28.4983, "lon": 77.2962 },
  "dl-VL-22": { "name": "Tughlakabad", "lat": 28.4874, "lon": 77.2990 },
  "dl-VL-23": { "name": "Badarpur Border", "lat": 28.4755, "lon": 77.3034 },
  "dl-VL-24": { "name": "Sarai", "lat": 28.4624, "lon": 77.3065 },
  "dl-VL-25": { "name": "NHPC Chowk", "lat": 28.4467, "lon": 77.3090 },
  "dl-VL-26": { "name": "Mewala Maharajpur", "lat": 28.4332, "lon": 77.3091 },
  "dl-VL-27": { "name": "Sector 28 Faridabad", "lat": 28.4200, "lon": 77.3104 },
  "dl-VL-28": { "name": "Badkal Mor", "lat": 28.4065, "lon": 77.3095 },
  "dl-VL-29": { "name": "Old Faridabad", "lat": 28.3930, "lon": 77.3082 },
  "dl-VL-30": { "name": "Neelam Chowk Ajronda", "lat": 28.3840, "lon": 77.3098 },
  "dl-VL-31": { "name": "Bata Chowk", "lat": 28.3748, "lon": 77.3092 },
  "dl-VL-32": { "name": "Escorts Mujesar", "lat": 28.3642, "lon": 77.3128 },
  "dl-VL-33": { "name": "Sant Surdas Sihi", "lat": 28.3530, "lon": 77.3158 },
  "dl-VL-34": { "name": "Raja Nahar Singh", "lat": 28.3418, "lon": 77.3195 },

  "dl-MG-01": { "name": "Botanical Garden", "lat": 28.5643, "lon": 77.3344 },
  "dl-MG-02": { "name": "Okhla Bird Sanctuary", "lat": 28.5577, "lon": 77.3196 },
  "dl-MG-03": { "name": "Kalindi Kunj", "lat": 28.5490, "lon": 77.3078 },
  "dl-MG-04": { "name": "Jasola Vihar Shaheen Bagh", "lat": 28.5408, "lon": 77.2938 },
  "dl-MG-05": { "name": "Okhla Vihar", "lat": 28.5369, "lon": 77.2797 },
  "dl-MG-06": { "name": "Jamia Millia Islamia", "lat": 28.5609, "lon": 77.2806 },
  "dl-MG-07": { "name": "Sukhdev Vihar", "lat": 28.5556, "lon": 77.2705 },
  "dl-MG-08": { "name": "Okhla NSIC", "lat": 28.5499, "lon": 77.2665 },
  "dl-MG-09": { "name": "Kalkaji Mandir", "lat": 28.5436, "lon": 77.2594 },
  "dl-MG-10": { "name": "Nehru Enclave", "lat": 28.5480, "lon": 77.2483 },
  "dl-MG-11": { "name": "Greater Kailash", "lat": 28.5475, "lon": 77.2354 },
  "dl-MG-12": { "name": "Chirag Delhi", "lat": 28.5436, "lon": 77.2221 },
  "dl-MG-13": { "name": "Panchsheel Park", "lat": 28.5423, "lon": 77.2125 },
  "dl-MG-14": { "name": "Hauz Khas", "lat": 28.5438, "lon": 77.2065 },
  "dl-MG-15": { "name": "IIT Delhi", "lat": 28.5473, "lon": 77.1918 },
  "dl-MG-16": { "name": "R.K. Puram", "lat": 28.5600, "lon": 77.1789 },
  "dl-MG-17": { "name": "Munirka", "lat": 28.5605, "lon": 77.1672 },
  "dl-MG-18": { "name": "Vasant Vihar", "lat": 28.5596, "lon": 77.1555 },
  "dl-MG-19": { "name": "Shankar Vihar", "lat": 28.5597, "lon": 77.1424 },
  "dl-MG-20": { "name": "Terminal 1 IGI Airport", "lat": 28.5630, "lon": 77.1195 },
  "dl-MG-21": { "name": "Sadar Bazaar Cantonment", "lat": 28.5699, "lon": 77.1025 },
  "dl-MG-22": { "name": "Palam", "lat": 28.5845, "lon": 77.0927 },
  "dl-MG-23": { "name": "Dashrath Puri", "lat": 28.5981, "lon": 77.0789 },
  "dl-MG-24": { "name": "Dabri Mor - Janakpuri South", "lat": 28.6108, "lon": 77.0650 },
  "dl-MG-25": { "name": "Janakpuri West", "lat": 28.6290, "lon": 77.0502 },

  "dl-PK-01": { "name": "Majlis Park", "lat": 28.7069, "lon": 77.1524 },
  "dl-PK-02": { "name": "Azadpur", "lat": 28.7073, "lon": 77.1792 },
  "dl-PK-03": { "name": "Shalimar Bagh", "lat": 28.7039, "lon": 77.1660 },
  "dl-PK-04": { "name": "Netaji Subhash Place", "lat": 28.6911, "lon": 77.1503 },
  "dl-PK-05": { "name": "Shakurpur", "lat": 28.6837, "lon": 77.1458 },
  "dl-PK-06": { "name": "Punjabi Bagh West", "lat": 28.6696, "lon": 77.1301 },
  "dl-PK-07": { "name": "ESI Basai Darapur", "lat": 28.6596, "lon": 77.1280 },
  "dl-PK-08": { "name": "Rajouri Garden", "lat": 28.6480, "lon": 77.1102 },
  "dl-PK-09": { "name": "Mayapuri", "lat": 28.6381, "lon": 77.1114 },
  "dl-PK-10": { "name": "Naraina Vihar", "lat": 28.6273, "lon": 77.1184 },
  "dl-PK-11": { "name": "Delhi Cantonment", "lat": 28.6119, "lon": 77.1293 },
  "dl-PK-12": { "name": "Durgabai Deshmukh South Campus", "lat": 28.5975, "lon": 77.1656 },
  "dl-PK-13": { "name": "Sir Vishweshwaraiah Moti Bagh", "lat": 28.5882, "lon": 77.1738 },
  "dl-PK-14": { "name": "Bhikaji Cama Place", "lat": 28.5744, "lon": 77.1859 },
  "dl-PK-15": { "name": "Sarojini Nagar", "lat": 28.5720, "lon": 77.1983 },
  "dl-PK-16": { "name": "INA", "lat": 28.5860, "lon": 77.2060 },
  "dl-PK-17": { "name": "South Extension", "lat": 28.5740, "lon": 77.2166 },
  "dl-PK-18": { "name": "Lajpat Nagar", "lat": 28.5701, "lon": 77.2438 },
  "dl-PK-19": { "name": "Vinobapuri", "lat": 28.5718, "lon": 77.2540 },
  "dl-PK-20": { "name": "Ashram", "lat": 28.5790, "lon": 77.2573 },
  "dl-PK-21": { "name": "Hazrat Nizamuddin", "lat": 28.5870, "lon": 77.2550 },
  "dl-PK-22": { "name": "Mayur Vihar Phase-I", "lat": 28.6049, "lon": 77.2897 },
  "dl-PK-23": { "name": "Mayur Vihar Pocket 1", "lat": 28.6076, "lon": 77.2989 },
  "dl-PK-24": { "name": "Trilokpuri Sanjay Lake", "lat": 28.6126, "lon": 77.3081 },
  "dl-PK-25": { "name": "Vinod Nagar East", "lat": 28.6210, "lon": 77.3058 },
  "dl-PK-26": { "name": "Vinod Nagar", "lat": 28.6257, "lon": 77.3068 },
  "dl-PK-27": { "name": "IP Extension", "lat": 28.6310, "lon": 77.3105 },
  "dl-PK-28": { "name": "Anand Vihar", "lat": 28.6461, "lon": 77.3159 },
  "dl-PK-29": { "name": "Karkarduma", "lat": 28.6456, "lon": 77.3068 },
  "dl-PK-30": { "name": "Karkarduma Court", "lat": 28.6502, "lon": 77.3109 },
  "dl-PK-31": { "name": "Krishna Nagar", "lat": 28.6563, "lon": 77.3017 },
  "dl-PK-32": { "name": "East Azad Nagar", "lat": 28.6609, "lon": 77.2918 },
  "dl-PK-33": { "name": "Welcome", "lat": 28.6729, "lon": 77.2650 },
  "dl-PK-34": { "name": "Jaffrabad", "lat": 28.6777, "lon": 77.2776 },
  "dl-PK-35": { "name": "Maujpur-Babarpur", "lat": 28.6841, "lon": 77.2866 },
  "dl-PK-36": { "name": "Gokulpuri", "lat": 28.6918, "lon": 77.2870 },
  "dl-PK-37": { "name": "Johri Enclave", "lat": 28.6995, "lon": 77.2952 },
  "dl-PK-38": { "name": "Shiv Vihar", "lat": 28.7066, "lon": 77.3035 },

  "dl-AE-01": { "name": "New Delhi", "lat": 28.6427, "lon": 77.2207 },
  "dl-AE-02": { "name": "Shivaji Stadium", "lat": 28.6259, "lon": 77.2129 },
  "dl-AE-03": { "name": "Dhaula Kuan", "lat": 28.5920, "lon": 77.1653 },
  "dl-AE-04": { "name": "Delhi Aerocity", "lat": 28.5569, "lon": 77.1197 },
  "dl-AE-05": { "name": "IGI Airport", "lat": 28.5563, "lon": 77.0896 },
  "dl-AE-06": { "name": "Dwarka Sector 21", "lat": 28.5523, "lon": 77.0583 }
}